peewee_moves.py
ex_peewee_moves-2.0.1.dist-info/LICENSE
ex_peewee_moves-2.0.1.dist-info/METADATA
ex_peewee_moves-2.0.1.dist-info/WHEEL
ex_peewee_moves-2.0.1.dist-info/entry_points.txt
ex_peewee_moves-2.0.1.dist-info/top_level.txt
ex_peewee_moves-2.0.1.dist-info/RECORD
